{
  "schema_version": "selection-record-v1",
  "round_id": "round-258",
  "roadmap_id": "2026-05-18-00-full-self-boot-end-to-end-roadmap",
  "roadmap_revision": "rev-001",
  "roadmap_dir": "orchestrator/roadmaps/2026-05-18-00-full-self-boot-end-to-end-roadmap/rev-001",
  "milestone_id": "milestone-1",
  "direction_id": "direction-1a-evidence-ledger-alignment",
  "extracted_item_id": "item-258-readiness-ledger-baseline-audit",
  "summary": "Audit and align the full self-boot readiness ledger and user-facing docs against the accepted ADR order and current compiler seed evidence.",
  "scheduler": {
    "depends_on_round_ids": [],
    "merge_after_item_ids": [],
    "parallel_group": null
  }
}
