{
  "schema_version": "selection-record-v1",
  "round_id": "round-243",
  "roadmap_id": "2026-05-16-00-architecture-deepening-roadmap",
  "roadmap_revision": "rev-001",
  "roadmap_dir": "orchestrator/roadmaps/2026-05-16-00-architecture-deepening-roadmap/rev-001",
  "milestone_id": "milestone-5",
  "direction_id": "direction-5a-prepared-generalization-artifact-depth",
  "extracted_item_id": "item-243-prepared-generalization-capability-adapters",
  "summary": "Move the normal pipeline's elaboration, root-generalization, and result-type reconstruction consumption of the Prepared Generalization Artifact behind owner APIs.",
  "scheduler": {
    "depends_on_round_ids": [],
    "merge_after_item_ids": [],
    "parallel_group": null
  }
}
